<?xml version="1.0" encoding="utf-8" ?><dwsync><file name="wp-super-cache-be_BY.mo" server="cooston.dreamhost.com/abundantenergy/" local="3402519060" remote="319783739046384148" Dst="-1" /><file name="wp-super-cache-be_BY.po" server="cooston.dreamhost.com/abundantenergy/" local="3402519060" remote="319783739046384148" Dst="-1" /><file name="wp-super-cache-de_DE.mo" server="cooston.dreamhost.com/abundantenergy/" local="3381439690" remote="319783739025304778" Dst="-1" /><file name="wp-super-cache-de_DE.po" server="cooston.dreamhost.com/abundantenergy/" local="3381439690" remote="319783739025304778" Dst="-1" /><file name="wp-super-cache-es_ES.mo" server="cooston.dreamhost.com/abundantenergy/" local="3340989216" remote="319783738984854304" Dst="-1" /><file name="wp-super-cache-es_ES.po" server="cooston.dreamhost.com/abundantenergy/" local="3340989216" remote="319783738984854304" Dst="-1" /><file name="wp-super-cache-fr_FR.mo" server="cooston.dreamhost.com/abundantenergy/" local="3368561556" remote="319783739012426644" Dst="-1" /><file name="wp-super-cache-fr_FR.po" server="cooston.dreamhost.com/abundantenergy/" local="3368561556" remote="319783739012426644" Dst="-1" /><file name="wp-super-cache-it_IT.mo" server="cooston.dreamhost.com/abundantenergy/" local="3373418278" remote="319783739017283366" Dst="-1" /><file name="wp-super-cache-it_IT.po" server="cooston.dreamhost.com/abundantenergy/" local="3373418278" remote="319783739017283366" Dst="-1" /><file name="wp-super-cache-ja.mo" server="cooston.dreamhost.com/abundantenergy/" local="3381416632" remote="319783739025281720" Dst="-1" /><file name="wp-super-cache-ja.po" server="cooston.dreamhost.com/abundantenergy/" local="3381416632" remote="319783739025281720" Dst="-1" /><file name="wp-super-cache-lt_LT.mo" server="cooston.dreamhost.com/abundantenergy/" local="3402518522" remote="319783739046383610" Dst="-1" /><file name="wp-super-cache-lt_LT.po" server="cooston.dreamhost.com/abundantenergy/" local="3402518522" remote="319783739046383610" Dst="-1" /><file name="wp-super-cache-ro_RO.mo" server="cooston.dreamhost.com/abundantenergy/" local="3402519390" remote="319783739046384478" Dst="-1" /><file name="wp-super-cache-ro_RO.po" server="cooston.dreamhost.com/abundantenergy/" local="3402519390" remote="319783739046384478" Dst="-1" /><file name="wp-super-cache-ru_RU.mo" server="cooston.dreamhost.com/abundantenergy/" local="3402519908" remote="319783739046384996" Dst="-1" /><file name="wp-super-cache-ru_RU.po" server="cooston.dreamhost.com/abundantenergy/" local="3402519908" remote="319783739046384996" Dst="-1" /><file name="wp-super-cache-sr_RS.mo" server="cooston.dreamhost.com/abundantenergy/" local="3451923332" remote="319783739095788420" Dst="-1" /><file name="wp-super-cache-sr_RS.po" server="cooston.dreamhost.com/abundantenergy/" local="3451923332" remote="319783739095788420" Dst="-1" /><file name="wp-super-cache-sv_SE.mo" server="cooston.dreamhost.com/abundantenergy/" local="3381359766" remote="319783739025224854" Dst="-1" /><file name="wp-super-cache-sv_SE.po" server="cooston.dreamhost.com/abundantenergy/" local="3381359766" remote="319783739025224854" Dst="-1" /><file name="wp-super-cache-tr_TR.mo" server="cooston.dreamhost.com/abundantenergy/" local="3381358668" remote="319783739025223756" Dst="-1" /><file name="wp-super-cache-tr_TR.po" server="cooston.dreamhost.com/abundantenergy/" local="3381358668" remote="319783739025223756" Dst="-1" /><file name="wp-super-cache-ua_UA.mo" server="cooston.dreamhost.com/abundantenergy/" local="3394657824" remote="319783739038522912" Dst="-1" /><file name="wp-super-cache-ua_UA.po" server="cooston.dreamhost.com/abundantenergy/" local="3394657824" remote="319783739038522912" Dst="-1" /><file name="wp-super-cache-uk.mo" server="cooston.dreamhost.com/abundantenergy/" local="3344354082" remote="319783738988219170" Dst="-1" /><file name="wp-super-cache-uk.po" server="cooston.dreamhost.com/abundantenergy/" local="3344354082" remote="319783738988219170" Dst="-1" /><file name="wp-super-cache-zh_CN.mo" server="cooston.dreamhost.com/abundantenergy/" local="3423140736" remote="319783739067005824" Dst="-1" /><file name="wp-super-cache-zh_CN.po" server="cooston.dreamhost.com/abundantenergy/" local="3426254234" remote="319783739070119322" Dst="-1" /><file name="wp-super-cache-zh_TW.mo" server="cooston.dreamhost.com/abundantenergy/" local="3423662042" remote="319783739067527130" Dst="-1" /><file name="wp-super-cache-zh_TW.po" server="cooston.dreamhost.com/abundantenergy/" local="3423662042" remote="319783739067527130" Dst="-1" /></dwsync>